{
	"data":[
		{
			"id":"10001",
			"jobb_post":"交互设计师",
			"brecm_img":true,
			"jobb_heart":false,
			"jobb_money":"15K-20K",
			"jobb_desc":"岗位短述",	
			"citys":"北京",
			"areas":"海淀区",
			"village":"中关村",
			"experience":"经验不限",
			"newIcon":"images/new_03.png",
			"mid":[
					"统招本科及以上学历，至少5年以上工作经验",
					"有ios平台和android平台相关开发作品或相关设计经验",
					"具有丰富的图标设计经验及相关成熟作品",
					"了解产品开发流程，有一定的交互设计经验者优先",
					"熟练使用photoshop、illustrator、ARP、AE等软件",
					"对教室行业感兴趣"
				],
			"bot":{
				"company":{
					"name":"特别厉害的大公司",
					"imgurl":"images/users.jpg",
					"desc":{
						"type":"互联网",
						"mold":"未融资",
						"size":"20-30人"
					}
				},
				"need":[
						"统招本科及以上学历至少5年以上工作经验",
						"有ios平台和android平台相关开发作品或相关设计经验",
						"具有丰富的图标设计经验及相关成熟作品",
						"了解产品开发流程，有一定的交互设计经验者优先",
						"熟练使用photoshop、illustrator、ARP、AE等软件",
						"对教室行业感兴趣"
				]
			}
		},
		{
			"id":"10002",
			"jobb_post":"UI设计师",
			"brecm_img":true,
			"jobb_heart":false,
			"jobb_money":"8K-15K",
			"jobb_desc":"岗位短述",	
			"citys":"北京",
			"areas":"东城区",
			"village":"银河SOHO",
			"experience":"经验不限",
			"newIcon":"images/new_03.png",
			"mid":[
					"统招本科及以上学历，至少5年以上工作经验",
					"有ios平台和android平台相关开发作品或相关设计经验",
					"具有丰富的图标设计经验及相关成熟作品",
					"了解产品开发流程，有一定的交互设计经验者优先",
					"熟练使用photoshop、illustrator、ARP、AE等软件",
					"对教室行业感兴趣"
				],
			"bot":{
				"company":{
					"name":"特别厉害的大公司",
					"imgurl":"images/users.jpg",
					"desc":{
						"type":"互联网",
						"mold":"未融资",
						"size":"20-30人"
					}
				},
				"need":[
						"统招本科及以上学历至少5年以上工作经验",
						"有ios平台和android平台相关开发作品或相关设计经验",
						"具有丰富的图标设计经验及相关成熟作品",
						"了解产品开发流程，有一定的交互设计经验者优先",
						"熟练使用photoshop、illustrator、ARP、AE等软件",
						"对教室行业感兴趣"
				]
			}
		},
		{
			"id":"10002",
			"jobb_post":"UI设计师",
			"brecm_img":true,
			"jobb_heart":false,
			"jobb_money":"8K-15K",
			"jobb_desc":"岗位短述",	
			"citys":"北京",
			"areas":"东城区",
			"village":"银河SOHO",
			"experience":"经验不限",
			"newIcon":"images/new_03.png",
			"mid":[
					"统招本科及以上学历，至少5年以上工作经验",
					"有ios平台和android平台相关开发作品或相关设计经验",
					"具有丰富的图标设计经验及相关成熟作品",
					"了解产品开发流程，有一定的交互设计经验者优先",
					"熟练使用photoshop、illustrator、ARP、AE等软件",
					"对教室行业感兴趣"
				],
			"bot":{
				"company":{
					"name":"特别厉害的大公司",
					"imgurl":"images/users.jpg",
					"desc":{
						"type":"互联网",
						"mold":"未融资",
						"size":"20-30人"
					}
				},
				"need":[
						"统招本科及以上学历至少5年以上工作经验",
						"有ios平台和android平台相关开发作品或相关设计经验",
						"具有丰富的图标设计经验及相关成熟作品",
						"了解产品开发流程，有一定的交互设计经验者优先",
						"熟练使用photoshop、illustrator、ARP、AE等软件",
						"对教室行业感兴趣"
				]
			}
		},
		{
			"id":"10002",
			"jobb_post":"UI设计师",
			"brecm_img":true,
			"jobb_heart":false,
			"jobb_money":"8K-15K",
			"jobb_desc":"岗位短述",	
			"citys":"北京",
			"areas":"东城区",
			"village":"银河SOHO",
			"experience":"经验不限",
			"newIcon":"images/new_03.png",
			"mid":[
					"统招本科及以上学历，至少5年以上工作经验",
					"有ios平台和android平台相关开发作品或相关设计经验",
					"具有丰富的图标设计经验及相关成熟作品",
					"了解产品开发流程，有一定的交互设计经验者优先",
					"熟练使用photoshop、illustrator、ARP、AE等软件",
					"对教室行业感兴趣"
				],
			"bot":{
				"company":{
					"name":"特别厉害的大公司",
					"imgurl":"images/users.jpg",
					"desc":{
						"type":"互联网",
						"mold":"未融资",
						"size":"20-30人"
					}
				},
				"need":[
						"统招本科及以上学历至少5年以上工作经验",
						"有ios平台和android平台相关开发作品或相关设计经验",
						"具有丰富的图标设计经验及相关成熟作品",
						"了解产品开发流程，有一定的交互设计经验者优先",
						"熟练使用photoshop、illustrator、ARP、AE等软件",
						"对教室行业感兴趣"
				]
			}
		},
		{
			"id":"10002",
			"jobb_post":"UI设计师",
			"brecm_img":true,
			"jobb_heart":false,
			"jobb_money":"8K-15K",
			"jobb_desc":"岗位短述",	
			"citys":"北京",
			"areas":"东城区",
			"village":"银河SOHO",
			"experience":"经验不限",
			"newIcon":"images/new_03.png",
			"mid":[
					"统招本科及以上学历，至少5年以上工作经验",
					"有ios平台和android平台相关开发作品或相关设计经验",
					"具有丰富的图标设计经验及相关成熟作品",
					"了解产品开发流程，有一定的交互设计经验者优先",
					"熟练使用photoshop、illustrator、ARP、AE等软件",
					"对教室行业感兴趣"
				],
			"bot":{
				"company":{
					"name":"特别厉害的大公司",
					"imgurl":"images/users.jpg",
					"desc":{
						"type":"互联网",
						"mold":"未融资",
						"size":"20-30人"
					}
				},
				"need":[
						"统招本科及以上学历至少5年以上工作经验",
						"有ios平台和android平台相关开发作品或相关设计经验",
						"具有丰富的图标设计经验及相关成熟作品",
						"了解产品开发流程，有一定的交互设计经验者优先",
						"熟练使用photoshop、illustrator、ARP、AE等软件",
						"对教室行业感兴趣"
				]
			}
		},
		{
			"id":"10002",
			"jobb_post":"UI设计师",
			"brecm_img":true,
			"jobb_heart":false,
			"jobb_money":"8K-15K",
			"jobb_desc":"岗位短述",	
			"citys":"北京",
			"areas":"东城区",
			"village":"银河SOHO",
			"experience":"经验不限",
			"newIcon":"images/new_03.png",
			"mid":[
					"统招本科及以上学历，至少5年以上工作经验",
					"有ios平台和android平台相关开发作品或相关设计经验",
					"具有丰富的图标设计经验及相关成熟作品",
					"了解产品开发流程，有一定的交互设计经验者优先",
					"熟练使用photoshop、illustrator、ARP、AE等软件",
					"对教室行业感兴趣"
				],
			"bot":{
				"company":{
					"name":"特别厉害的大公司",
					"imgurl":"images/users.jpg",
					"desc":{
						"type":"互联网",
						"mold":"未融资",
						"size":"20-30人"
					}
				},
				"need":[
						"统招本科及以上学历至少5年以上工作经验",
						"有ios平台和android平台相关开发作品或相关设计经验",
						"具有丰富的图标设计经验及相关成熟作品",
						"了解产品开发流程，有一定的交互设计经验者优先",
						"熟练使用photoshop、illustrator、ARP、AE等软件",
						"对教室行业感兴趣"
				]
			}
		},
		{
			"id":"10002",
			"jobb_post":"UI设计师",
			"brecm_img":true,
			"jobb_heart":false,
			"jobb_money":"8K-15K",
			"jobb_desc":"岗位短述",	
			"citys":"北京",
			"areas":"东城区",
			"village":"银河SOHO",
			"experience":"经验不限",
			"newIcon":"images/new_03.png",
			"mid":[
					"统招本科及以上学历，至少5年以上工作经验",
					"有ios平台和android平台相关开发作品或相关设计经验",
					"具有丰富的图标设计经验及相关成熟作品",
					"了解产品开发流程，有一定的交互设计经验者优先",
					"熟练使用photoshop、illustrator、ARP、AE等软件",
					"对教室行业感兴趣"
				],
			"bot":{
				"company":{
					"name":"特别厉害的大公司",
					"imgurl":"images/users.jpg",
					"desc":{
						"type":"互联网",
						"mold":"未融资",
						"size":"20-30人"
					}
				},
				"need":[
						"统招本科及以上学历至少5年以上工作经验",
						"有ios平台和android平台相关开发作品或相关设计经验",
						"具有丰富的图标设计经验及相关成熟作品",
						"了解产品开发流程，有一定的交互设计经验者优先",
						"熟练使用photoshop、illustrator、ARP、AE等软件",
						"对教室行业感兴趣"
				]
			}
		},
		{
			"id":"10002",
			"jobb_post":"UI设计师",
			"brecm_img":true,
			"jobb_heart":false,
			"jobb_money":"8K-15K",
			"jobb_desc":"岗位短述",	
			"citys":"北京",
			"areas":"东城区",
			"village":"银河SOHO",
			"experience":"经验不限",
			"newIcon":"images/new_03.png",
			"mid":[
					"统招本科及以上学历，至少5年以上工作经验",
					"有ios平台和android平台相关开发作品或相关设计经验",
					"具有丰富的图标设计经验及相关成熟作品",
					"了解产品开发流程，有一定的交互设计经验者优先",
					"熟练使用photoshop、illustrator、ARP、AE等软件",
					"对教室行业感兴趣"
				],
			"bot":{
				"company":{
					"name":"特别厉害的大公司",
					"imgurl":"images/users.jpg",
					"desc":{
						"type":"互联网",
						"mold":"未融资",
						"size":"20-30人"
					}
				},
				"need":[
						"统招本科及以上学历至少5年以上工作经验",
						"有ios平台和android平台相关开发作品或相关设计经验",
						"具有丰富的图标设计经验及相关成熟作品",
						"了解产品开发流程，有一定的交互设计经验者优先",
						"熟练使用photoshop、illustrator、ARP、AE等软件",
						"对教室行业感兴趣"
				]
			}
		},
		{
			"id":"10002",
			"jobb_post":"UI设计师",
			"brecm_img":true,
			"jobb_heart":false,
			"jobb_money":"8K-15K",
			"jobb_desc":"岗位短述",	
			"citys":"北京",
			"areas":"东城区",
			"village":"银河SOHO",
			"experience":"经验不限",
			"newIcon":"images/new_03.png",
			"mid":[
					"统招本科及以上学历，至少5年以上工作经验",
					"有ios平台和android平台相关开发作品或相关设计经验",
					"具有丰富的图标设计经验及相关成熟作品",
					"了解产品开发流程，有一定的交互设计经验者优先",
					"熟练使用photoshop、illustrator、ARP、AE等软件",
					"对教室行业感兴趣"
				],
			"bot":{
				"company":{
					"name":"特别厉害的大公司",
					"imgurl":"images/users.jpg",
					"desc":{
						"type":"互联网",
						"mold":"未融资",
						"size":"20-30人"
					}
				},
				"need":[
						"统招本科及以上学历至少5年以上工作经验",
						"有ios平台和android平台相关开发作品或相关设计经验",
						"具有丰富的图标设计经验及相关成熟作品",
						"了解产品开发流程，有一定的交互设计经验者优先",
						"熟练使用photoshop、illustrator、ARP、AE等软件",
						"对教室行业感兴趣"
				]
			}
		},
		{
			"id":"10002",
			"jobb_post":"UI设计师",
			"brecm_img":true,
			"jobb_heart":false,
			"jobb_money":"8K-15K",
			"jobb_desc":"岗位短述",	
			"citys":"北京",
			"areas":"东城区",
			"village":"银河SOHO",
			"experience":"经验不限",
			"newIcon":"images/new_03.png",
			"mid":[
					"统招本科及以上学历，至少5年以上工作经验",
					"有ios平台和android平台相关开发作品或相关设计经验",
					"具有丰富的图标设计经验及相关成熟作品",
					"了解产品开发流程，有一定的交互设计经验者优先",
					"熟练使用photoshop、illustrator、ARP、AE等软件",
					"对教室行业感兴趣"
				],
			"bot":{
				"company":{
					"name":"特别厉害的大公司",
					"imgurl":"images/users.jpg",
					"desc":{
						"type":"互联网",
						"mold":"未融资",
						"size":"20-30人"
					}
				},
				"need":[
						"统招本科及以上学历至少5年以上工作经验",
						"有ios平台和android平台相关开发作品或相关设计经验",
						"具有丰富的图标设计经验及相关成熟作品",
						"了解产品开发流程，有一定的交互设计经验者优先",
						"熟练使用photoshop、illustrator、ARP、AE等软件",
						"对教室行业感兴趣"
				]
			}
		},
		{
			"id":"10002",
			"jobb_post":"UI设计师",
			"brecm_img":true,
			"jobb_heart":false,
			"jobb_money":"8K-15K",
			"jobb_desc":"岗位短述",	
			"citys":"北京",
			"areas":"东城区",
			"village":"银河SOHO",
			"experience":"经验不限",
			"newIcon":"images/new_03.png",
			"mid":[
					"统招本科及以上学历，至少5年以上工作经验",
					"有ios平台和android平台相关开发作品或相关设计经验",
					"具有丰富的图标设计经验及相关成熟作品",
					"了解产品开发流程，有一定的交互设计经验者优先",
					"熟练使用photoshop、illustrator、ARP、AE等软件",
					"对教室行业感兴趣"
				],
			"bot":{
				"company":{
					"name":"特别厉害的大公司",
					"imgurl":"images/users.jpg",
					"desc":{
						"type":"互联网",
						"mold":"未融资",
						"size":"20-30人"
					}
				},
				"need":[
						"统招本科及以上学历至少5年以上工作经验",
						"有ios平台和android平台相关开发作品或相关设计经验",
						"具有丰富的图标设计经验及相关成熟作品",
						"了解产品开发流程，有一定的交互设计经验者优先",
						"熟练使用photoshop、illustrator、ARP、AE等软件",
						"对教室行业感兴趣"
				]
			}
		},
		{
			"id":"10002",
			"jobb_post":"UI设计师",
			"brecm_img":true,
			"jobb_heart":false,
			"jobb_money":"8K-15K",
			"jobb_desc":"岗位短述",	
			"citys":"北京",
			"areas":"东城区",
			"village":"银河SOHO",
			"experience":"经验不限",
			"newIcon":"images/new_03.png",
			"mid":[
					"统招本科及以上学历，至少5年以上工作经验",
					"有ios平台和android平台相关开发作品或相关设计经验",
					"具有丰富的图标设计经验及相关成熟作品",
					"了解产品开发流程，有一定的交互设计经验者优先",
					"熟练使用photoshop、illustrator、ARP、AE等软件",
					"对教室行业感兴趣"
				],
			"bot":{
				"company":{
					"name":"特别厉害的大公司",
					"imgurl":"images/users.jpg",
					"desc":{
						"type":"互联网",
						"mold":"未融资",
						"size":"20-30人"
					}
				},
				"need":[
						"统招本科及以上学历至少5年以上工作经验",
						"有ios平台和android平台相关开发作品或相关设计经验",
						"具有丰富的图标设计经验及相关成熟作品",
						"了解产品开发流程，有一定的交互设计经验者优先",
						"熟练使用photoshop、illustrator、ARP、AE等软件",
						"对教室行业感兴趣"
				]
			}
		},
		{
			"id":"10002",
			"jobb_post":"UI设计师",
			"brecm_img":true,
			"jobb_heart":false,
			"jobb_money":"8K-15K",
			"jobb_desc":"岗位短述",	
			"citys":"北京",
			"areas":"东城区",
			"village":"银河SOHO",
			"experience":"经验不限",
			"newIcon":"images/new_03.png",
			"mid":[
					"统招本科及以上学历，至少5年以上工作经验",
					"有ios平台和android平台相关开发作品或相关设计经验",
					"具有丰富的图标设计经验及相关成熟作品",
					"了解产品开发流程，有一定的交互设计经验者优先",
					"熟练使用photoshop、illustrator、ARP、AE等软件",
					"对教室行业感兴趣"
				],
			"bot":{
				"company":{
					"name":"特别厉害的大公司",
					"imgurl":"images/users.jpg",
					"desc":{
						"type":"互联网",
						"mold":"未融资",
						"size":"20-30人"
					}
				},
				"need":[
						"统招本科及以上学历至少5年以上工作经验",
						"有ios平台和android平台相关开发作品或相关设计经验",
						"具有丰富的图标设计经验及相关成熟作品",
						"了解产品开发流程，有一定的交互设计经验者优先",
						"熟练使用photoshop、illustrator、ARP、AE等软件",
						"对教室行业感兴趣"
				]
			}
		},
		{
			"id":"10002",
			"jobb_post":"UI设计师",
			"brecm_img":true,
			"jobb_heart":false,
			"jobb_money":"8K-15K",
			"jobb_desc":"岗位短述",	
			"citys":"北京",
			"areas":"东城区",
			"village":"银河SOHO",
			"experience":"经验不限",
			"newIcon":"images/new_03.png",
			"mid":[
					"统招本科及以上学历，至少5年以上工作经验",
					"有ios平台和android平台相关开发作品或相关设计经验",
					"具有丰富的图标设计经验及相关成熟作品",
					"了解产品开发流程，有一定的交互设计经验者优先",
					"熟练使用photoshop、illustrator、ARP、AE等软件",
					"对教室行业感兴趣"
				],
			"bot":{
				"company":{
					"name":"特别厉害的大公司",
					"imgurl":"images/users.jpg",
					"desc":{
						"type":"互联网",
						"mold":"未融资",
						"size":"20-30人"
					}
				},
				"need":[
						"统招本科及以上学历至少5年以上工作经验",
						"有ios平台和android平台相关开发作品或相关设计经验",
						"具有丰富的图标设计经验及相关成熟作品",
						"了解产品开发流程，有一定的交互设计经验者优先",
						"熟练使用photoshop、illustrator、ARP、AE等软件",
						"对教室行业感兴趣"
				]
			}
		},
		{
			"id":"10002",
			"jobb_post":"UI设计师",
			"brecm_img":true,
			"jobb_heart":false,
			"jobb_money":"8K-15K",
			"jobb_desc":"岗位短述",	
			"citys":"北京",
			"areas":"东城区",
			"village":"银河SOHO",
			"experience":"经验不限",
			"newIcon":"images/new_03.png",
			"mid":[
					"统招本科及以上学历，至少5年以上工作经验",
					"有ios平台和android平台相关开发作品或相关设计经验",
					"具有丰富的图标设计经验及相关成熟作品",
					"了解产品开发流程，有一定的交互设计经验者优先",
					"熟练使用photoshop、illustrator、ARP、AE等软件",
					"对教室行业感兴趣"
				],
			"bot":{
				"company":{
					"name":"特别厉害的大公司",
					"imgurl":"images/users.jpg",
					"desc":{
						"type":"互联网",
						"mold":"未融资",
						"size":"20-30人"
					}
				},
				"need":[
						"统招本科及以上学历至少5年以上工作经验",
						"有ios平台和android平台相关开发作品或相关设计经验",
						"具有丰富的图标设计经验及相关成熟作品",
						"了解产品开发流程，有一定的交互设计经验者优先",
						"熟练使用photoshop、illustrator、ARP、AE等软件",
						"对教室行业感兴趣"
				]
			}
		},
		{
			"id":"10002",
			"jobb_post":"UI设计师",
			"brecm_img":true,
			"jobb_heart":false,
			"jobb_money":"8K-15K",
			"jobb_desc":"岗位短述",	
			"citys":"北京",
			"areas":"东城区",
			"village":"银河SOHO",
			"experience":"经验不限",
			"newIcon":"images/new_03.png",
			"mid":[
					"统招本科及以上学历，至少5年以上工作经验",
					"有ios平台和android平台相关开发作品或相关设计经验",
					"具有丰富的图标设计经验及相关成熟作品",
					"了解产品开发流程，有一定的交互设计经验者优先",
					"熟练使用photoshop、illustrator、ARP、AE等软件",
					"对教室行业感兴趣"
				],
			"bot":{
				"company":{
					"name":"特别厉害的大公司",
					"imgurl":"images/users.jpg",
					"desc":{
						"type":"互联网",
						"mold":"未融资",
						"size":"20-30人"
					}
				},
				"need":[
						"统招本科及以上学历至少5年以上工作经验",
						"有ios平台和android平台相关开发作品或相关设计经验",
						"具有丰富的图标设计经验及相关成熟作品",
						"了解产品开发流程，有一定的交互设计经验者优先",
						"熟练使用photoshop、illustrator、ARP、AE等软件",
						"对教室行业感兴趣"
				]
			}
		}
	],
	"user":{
		"name":"张三",
		"major":"web前端",
		"days":"91",
		"ends":"90",
		"mark":"87",
		"jump":[
			{
				"id":"10002",
				"number":"2"
			}
		],
		"jumpSum":"2"
	}

}